{
    "tools": [
        {
            "type": "*",
            "enabled": false
        },
        {
            "type": "toolbar",
            "enabled": false
        },
        {
            "type": "shortcut-menu",
            "enabled": true
        },
        {
            "type": "measure",
            "enabled": true,
            "position": "shortcut-menu"
        },
        {
            "type": "about",
            "enabled": true,
            "position": "shortcut-menu",
            "content": "About this map"
        },
        {
            "type": "layers",
            "enabled": true,
            "position": "shortcut-menu"
        }
    ]
}